{
  "en": {
    "layout": {

      "menu": {
        "home": "Home",
        "tours": "Tours",
        "register": "Register",
        "login": "Login",
        "lightMode": "Light mode",
        "darkMode": "Dark mode",
        "language": "Language",
        "exit": "Exit",
        "edit": "Edit",
        "reservation": "Reservation"
      },

      "footer": {
        "poweredBy": "Powered by ASSkii Sotona"
      }

    }
  },

  "kz": {
    "layout": {

      "menu": {
        "home": "Басты бет",
        "tours": "Турлар",
        "register": "Тіркелу",
        "login": "Кіру",
        "lightMode": "Жарық режим",
        "darkMode": "Қараңғы режимі",
        "language": "Тіл",
        "exit": "Шығу",
        "edit": "Профильді өзгерту",
        "reservation": "Брондауға запростар"
      },

      "footer": {
        "poweredBy": "Істеген АЦЦкий Сотона"
      }

    }
  },

  "ru": {
    "layout": {

      "menu": {
        "home": "Главная",
        "tours": "Туры",
        "register": "Регистрация",
        "login": "Войти",
        "lightMode": "Эльфийский режим",
        "darkMode": "Негрский режим",
        "language": "Язык",
        "exit": "Выйти",
        "edit": "Изменить профиль",
        "reservation": "Запросы на бронь"
      },

      "footer": {
        "poweredBy": "Сделано Аццкой Сотоной"
      }

    }
  }
}